{
  "project_info": {
    "project_number": "455321813959",
    "project_id": "ecommerce-1e01a",
    "storage_bucket": "ecommerce-1e01a.appspot.com"
  },
  "client": [
    {
      "client_info": {
        "mobilesdk_app_id": "1:455321813959:android:763b6c4b2121a65f150fe2",
        "android_client_info": {
          "package_name": "com.example.myapp"
        }
      },
      "oauth_client": [],
      "api_key": [
        {
          "current_key": "AIzaSyAFMV2xcDZ59VjqTpe0uPo-q_yD7xBOopY"
        }
      ],
      "services": {
        "appinvite_service": {
          "other_platform_oauth_client": []
        }
      }
    }
  ],
  "configuration_version": "1"
}